<annotation>
	<folder>train</folder>
	<filename>011.jpg</filename>
	<path>/home/akshay/Documents/ObjectDetectionCustom/models/research/object_detection/images/train/011.jpg</path>
	<source>
		<database>Unknown</database>
	</source>
	<size>
		<width>321</width>
		<height>400</height>
		<depth>3</depth>
	</size>
	<segmented>0</segmented>
	<object>
		<name>Senior Citizen</name>
		<pose>Unspecified</pose>
		<truncated>0</truncated>
		<difficult>0</difficult>
		<bndbox>
			<xmin>51</xmin>
			<ymin>45</ymin>
			<xmax>284</xmax>
			<ymax>286</ymax>
		</bndbox>
	</object>
</annotation>
